spotify_recommendation_mcp/__init__.py
spotify_recommendation_mcp/server.py
spotify_recommendation_mcp-0.2.0.dist-info/licenses/LICENSE
spotify_recommendation_mcp-0.2.0.dist-info/METADATA
spotify_recommendation_mcp-0.2.0.dist-info/WHEEL
spotify_recommendation_mcp-0.2.0.dist-info/entry_points.txt
spotify_recommendation_mcp-0.2.0.dist-info/top_level.txt
spotify_recommendation_mcp-0.2.0.dist-info/RECORD
